pythonvideoannotator_module_tracking/__init__.py
pythonvideoannotator_module_tracking/code_template.py
pythonvideoannotator_module_tracking/module.py
pythonvideoannotator_module_tracking/tracking_window.py
pythonvideoannotator_module_tracking/module_mcvapi/__init__.py
pythonvideoannotator_module_tracking/module_mcvapi/blobs/__init__.py
pythonvideoannotator_module_tracking/module_mcvapi/blobs/sort_paths.py
pythonvideoannotator_module_tracking/module_mcvapi/masks/__init__.py
pythonvideoannotator_module_tracking/module_mcvapi/masks/path_mask.py
pythonvideoannotator_module_tracking/module_mcvgui/__init__.py
pythonvideoannotator_module_tracking/module_mcvgui/blobs/__init__.py
pythonvideoannotator_module_tracking/module_mcvgui/blobs/sort_paths.py
pythonvideoannotator_module_tracking/module_mcvgui/dialogs/__init__.py
pythonvideoannotator_module_tracking/module_mcvgui/dialogs/tracking_filter.py
pythonvideoannotator_module_tracking/module_mcvgui/filters/__init__.py
pythonvideoannotator_module_tracking/module_mcvgui/filters/background_subtract.py
pythonvideoannotator_module_tracking/module_mcvgui/masks/__init__.py
pythonvideoannotator_module_tracking/module_mcvgui/masks/path_mask.py
pythonvideoannotator_module_tracking/module_mcvgui/masks/polygons_mask.py
Python_video_annotator_module_tracking-0.6.38.dist-info/METADATA
Python_video_annotator_module_tracking-0.6.38.dist-info/WHEEL
Python_video_annotator_module_tracking-0.6.38.dist-info/top_level.txt
Python_video_annotator_module_tracking-0.6.38.dist-info/RECORD
